generate_doc/__init__.py
generate_doc/generate_doc.py
generate_doc-1.0.dist-info/METADATA
generate_doc-1.0.dist-info/WHEEL
generate_doc-1.0.dist-info/entry_points.txt
generate_doc-1.0.dist-info/top_level.txt
generate_doc-1.0.dist-info/RECORD
