Metadata-Version: 2.1
Name: generate-doc
Version: 1.0
Requires-Dist: aiohttp (==3.8.4)
Requires-Dist: aiosignal (==1.3.1)
Requires-Dist: async-timeout (==4.0.2)
Requires-Dist: attrs (==23.1.0)
Requires-Dist: certifi (==2023.5.7)
Requires-Dist: charset-normalizer (==3.1.0)
Requires-Dist: frozenlist (==1.3.3)
Requires-Dist: idna (==3.4)
Requires-Dist: multidict (==6.0.4)
Requires-Dist: numpy (==1.24.3)
Requires-Dist: openai (==0.27.8)
Requires-Dist: python-dotenv (==1.0.0)
Requires-Dist: requests (==2.31.0)
Requires-Dist: tqdm (==4.65.0)
Requires-Dist: urllib3 (==2.0.3)
Requires-Dist: yarl (==1.9.2)
